LICENSE
MANIFEST.in
README.md
setup.cfg
setup.py
BibaAndBoba/__init__.py
BibaAndBoba/biba_and_boba.py
BibaAndBoba/comparator.py
BibaAndBoba.egg-info/PKG-INFO
BibaAndBoba.egg-info/SOURCES.txt
BibaAndBoba.egg-info/dependency_links.txt
BibaAndBoba.egg-info/not-zip-safe
BibaAndBoba.egg-info/requires.txt
BibaAndBoba.egg-info/top_level.txt
BibaAndBoba/dictionaries/base_ua.txt
BibaAndBoba/dictionaries/stopwords.txt
BibaAndBoba/docs/requirements-docs.txt
BibaAndBoba/docs/build/html/_sources/BibaAndBoba.rst.txt
BibaAndBoba/docs/build/html/_sources/index.rst.txt
BibaAndBoba/docs/build/html/_static/scripts/furo.js.LICENSE.txt
BibaAndBoba/utils/__init__.py
BibaAndBoba/utils/cacher.py
BibaAndBoba/utils/logger.py
BibaAndBoba/utils/nltk_punkt_downloader.py
BibaAndBoba/utils/progress_bar.py
BibaAndBoba/utils/reader.py
BibaAndBoba/utils/tokenizer.py
tests/__init__.py
tests/conftest.py
tests/test_biba_and_boba.py
tests/test_comparator.py
tests/test_nltk_punkt_downloader.py
tests/test_reader.py